graphtools/__init__.py
graphtools/api.py
graphtools/base.py
graphtools/estimator.py
graphtools/graphs.py
graphtools/matrix.py
graphtools/utils.py
graphtools/version.py
graphtools-2.0.0.dist-info/licenses/LICENSE
graphtools-2.0.0.dist-info/METADATA
graphtools-2.0.0.dist-info/WHEEL
graphtools-2.0.0.dist-info/top_level.txt
graphtools-2.0.0.dist-info/RECORD
