Metadata-Version: 2.4
Name: graphtools
Version: 2.0.0
Summary: graphtools
Home-page: https://github.com/KrishnaswamyLab/graphtools
Download-URL: https://github.com/KrishnaswamyLab/graphtools/archive/v2.0.0.tar.gz
Author: Scott Gigante, Daniel Burkhardt, and Jay Stanley, Yale University
Author-email: scott.gigante@yale.edu
License: GNU General Public License Version 2
Keywords: graphs,big-data,signal processing,manifold-learning
Classifier: Development Status :: 4 - Beta
Classifier: Environment :: Console
Classifier: Framework :: Jupyter
Classifier: Intended Audience :: Developers
Classifier: Intended Audience :: Science/Research
Classifier: Natural Language :: English
Classifier: Operating System :: MacOS :: MacOS X
Classifier: Operating System :: Microsoft :: Windows
Classifier: Operating System :: POSIX :: Linux
Classifier: Programming Language :: Python :: 2
Classifier: Programming Language :: Python :: 2.7
Classifier: Programming Language :: Python :: 3
Classifier: Programming Language :: Python :: 3.5
Classifier: Programming Language :: Python :: 3.6
Classifier: Topic :: Scientific/Engineering :: Mathematics
License-File: LICENSE
Requires-Dist: numpy>=1.14.0
Requires-Dist: scipy>=1.1.0
Requires-Dist: pygsp>=0.5.1
Requires-Dist: scikit-learn>=0.20.0
Requires-Dist: future
Requires-Dist: tasklogger>=1.0
Requires-Dist: Deprecated
Provides-Extra: test
Requires-Dist: nose; extra == "test"
Requires-Dist: nose2; extra == "test"
Requires-Dist: pandas; extra == "test"
Requires-Dist: coverage; extra == "test"
Requires-Dist: coveralls; extra == "test"
Requires-Dist: python-igraph; extra == "test"
Requires-Dist: parameterized; extra == "test"
Requires-Dist: anndata; extra == "test"
Requires-Dist: anndata; extra == "test"
Requires-Dist: black; extra == "test"
Provides-Extra: doc
Requires-Dist: sphinx; extra == "doc"
Requires-Dist: sphinxcontrib-napoleon; extra == "doc"
Requires-Dist: sphinxcontrib-bibtex; extra == "doc"
Provides-Extra: numba
Requires-Dist: numba>=0.50.0; extra == "numba"
Provides-Extra: fast
Requires-Dist: numba>=0.50.0; extra == "fast"
Provides-Extra: all
Requires-Dist: nose; extra == "all"
Requires-Dist: nose2; extra == "all"
Requires-Dist: pandas; extra == "all"
Requires-Dist: coverage; extra == "all"
Requires-Dist: coveralls; extra == "all"
Requires-Dist: python-igraph; extra == "all"
Requires-Dist: parameterized; extra == "all"
Requires-Dist: anndata; extra == "all"
Requires-Dist: anndata; extra == "all"
Requires-Dist: sphinx; extra == "all"
Requires-Dist: sphinxcontrib-napoleon; extra == "all"
Requires-Dist: sphinxcontrib-bibtex; extra == "all"
Requires-Dist: numba>=0.50.0; extra == "all"
Dynamic: author
Dynamic: author-email
Dynamic: classifier
Dynamic: description
Dynamic: download-url
Dynamic: home-page
Dynamic: keywords
Dynamic: license
Dynamic: license-file
Dynamic: provides-extra
Dynamic: requires-dist
Dynamic: summary
